
	[{
		"name":"Battista",
		"type": "dining",
		"shape": "rectangle",
		"size": "large",
		"style": "modern",
		"material":"wood",
		"image":"http://placehold.it/350x150"
		
	},
	{
		"name": "Baldwin",
		"type": "coffee",
		"shape": "square",
		"size": "medium",
		"style": "transitdional",
		"material":"wood"
		
	},
	{
		"name":"capri",
		"type": "cocktail",
		"shape": "round",
		"size": "small",
		"style": "modern",
		"material":"metal"
		
	},
	{
		"name":"Continental",
		"type": "dining",
		"shape": "round",
		"size": "large",
		"style": "modern",
		"material":"wood"

	},
{
		"name":"Aurelia",
		"type": "dining",
		"shape": "rectangle",
		"size": "large",
		"style": "modern",
		"material":"wood"

	},
	{
		"name":"Elgin",
		"type": "coffee",
		"shape": "rectangle",
		"size": "medium",
		"style": "modern",
		"material":"metal"

	},
{
		"name":"Poiret",
		"type": "coffee",
		"shape": "round",
		"size": "medium",
		"style": "modern",
		"material":"wood"

	},
	{
		"name":"Hepworth",
		"type": "side",
		"shape": "square",
		"size": "small",
		"style": "transitional",
		"material":"other"

	},
{
		"name":"Vienna",
		"type": "side",
		"shape": "round",
		"size": "medium",
		"style": "traditional",
		"material":"wood"

	},
	{
		"name":"Thebes",
		"type": "side",
		"shape": "square",
		"size": "small",
		"style": "modern",
		"material":"metal"

	},
	{
		"name":"Austrian",
		"type": "dining",
		"shape": "round",
		"size": "large",
		"style": "traditional",
		"material":"wood"

	},
	{
		"name":"Nanking",
		"type": "coffee",
		"shape": "square",
		"size": "medium",
		"style": "traditional",
		"material":"wood"

	},
	{
		"name":"Marbella",
		"type": "coffee",
		"shape": "rectangle",
		"size": "medium",
		"style": "traditional",
		"material":"metal"

	},
	{
		"name":"Chengtu",
		"type": "coffee",
		"shape": "square",
		"size": "medium",
		"style": "transitional",
		"material":"wood"

	},
	{
		"name":"Hansen",
		"type": "side",
		"shape": "round",
		"size": "small",
		"style": "transitional",
		"material":"wood"

	},
	{
		"name":"Boldini",
		"type": "dining",
		"shape": "round",
		"size": "large",
		"style": "transitional",
		"material":"wood"

	},
{
		"name":"Gombe",
		"type": "side",
		"shape": "round",
		"size": "medium",
		"style": "transitional",
		"material":"other"

	},
{
		"name":"Maxime",
		"type": "side",
		"shape": "square",
		"size": "medium",
		"style": "transitional",
		"material":"other"

	}]


